adam_fo-0.0.2.dist-info/METADATA
adam_fo-0.0.2.dist-info/WHEEL
adam_fo-0.0.2.dist-info/entry_points.txt
adam_fo/.env
adam_fo/__init__.py
adam_fo/_version.py
adam_fo/build.py
adam_fo/build_fo.sh
adam_fo/config.py
adam_fo/conversions.py
adam_fo/environ.dat.tpl
adam_fo/run_fo.py
adam_fo-0.0.2.dist-info/RECORD
