Metadata-Version: 2.1
Name: adam-fo
Version: 0.0.2
Summary: Wrapper for Bill Gray's fo, the programmatic version of find_orb
Author-Email: Alec Koumjian <alec@b612foundation.org>
License: GPL-3.0
Requires-Python: <3.13,>=3.11
Requires-Dist: adam-core>=0.3.6
Provides-Extra: test
Requires-Dist: black>=24.10.0; extra == "test"
Requires-Dist: ruff>=0.9.2; extra == "test"
Requires-Dist: isort>=5.13.2; extra == "test"
Requires-Dist: mypy>=1.14.1; extra == "test"
Requires-Dist: pytest>=8.3.4; extra == "test"
